tuling/__init__.py
tuling-1.2.dist-info/METADATA
tuling-1.2.dist-info/WHEEL
tuling-1.2.dist-info/top_level.txt
tuling-1.2.dist-info/RECORD
