Metadata-Version: 2.1
Name: tuling
Version: 1.2
Summary: 基于python的小图灵api库
Home-page: https://wuyuan.dev
Author: qqcd，孙悟元
Author-email: 1847261658@qq.com
Maintainer: qqcd，孙悟元
Maintainer-email: 1847261658@qq.com
License: MIT License
Classifier: Development Status :: 3 - Alpha
Classifier: Intended Audience :: Developers
Classifier: Topic :: Software Development :: Build Tools
Classifier: License :: OSI Approved :: MIT License
Classifier: Programming Language :: Python :: 3
Requires-Python: >=3.9
